fluent/__init__.py
fluent/resource.py
fluenticons-2.0.0.dist-info/METADATA
fluenticons-2.0.0.dist-info/WHEEL
fluenticons-2.0.0.dist-info/RECORD
